{
  "project_info": {
    "project_number": "635740991663",
    "project_id": "prepaid-smartel-621bb",
    "storage_bucket": "prepaid-smartel-621bb.appspot.com"
  },
  "client": [
    {
      "client_info": {
        "mobilesdk_app_id": "1:635740991663:android:7efd22e1582f222aeb245a",
        "android_client_info": {
          "package_name": "com.example.prepaid_smartel"
        }
      },
      "oauth_client": [
        {
          "client_id": "635740991663-prle1q6a0tieb64efkn6cpri2p5182nd.apps.googleusercontent.com",
          "client_type": 3
        }
      ],
      "api_key": [
        {
          "current_key": "AIzaSyC0FZjGKr61JXYfjRPNPbpD_1kyyB8dAOU"
        }
      ],
      "services": {
        "appinvite_service": {
          "other_platform_oauth_client": [
            {
              "client_id": "635740991663-prle1q6a0tieb64efkn6cpri2p5182nd.apps.googleusercontent.com",
              "client_type": 3
            }
          ]
        }
      }
    }
  ],
  "configuration_version": "1"
}